pogodb.py
pogodb-0.0.3.dist-info/LICENSE.txt
pogodb-0.0.3.dist-info/WHEEL
pogodb-0.0.3.dist-info/METADATA
pogodb-0.0.3.dist-info/RECORD
