Metadata-Version: 2.1
Name: pogodb
Version: 0.0.3
Summary: PogoDB: Simple NoSQL wrapper around Postgres' JSONB type.
Home-page: https://github.com/polydojo/pogodb
License: UNKNOWN
Author: Polydojo, Inc.
Author-email: 8079593+sumukhbarve@users.noreply.github.com
Classifier: License :: OSI Approved :: Apache Software License
Requires-Dist: dotsi >=0.0.1
